<?xml version="1.0" encoding="UTF-8"?>
<beans xmlns="http://www.springframework.org/schema/beans"
       xmlns:xsi="http://www.w3.org/2001/XMLSchema-instance"
       xmlns:context="http://www.springframework.org/schema/context"
       xmlns:p="http://www.springframework.org/schema/p"
       xsi:schemaLocation="http://www.springframework.org/schema/beans
       http://www.springframework.org/schema/beans/spring-beans.xsd
       http://www.springframework.org/schema/context
       http://www.springframework.org/schema/context/spring-context.xsd">

    <context:component-scan base-package="com.persistence"/>

    <bean id="dataSource" class="org.apache.commons.dbcp.BasicDataSource"
          p:driverClassName="${spring.datasource.driver-class-name}"
          p:url="${spring.datasource.url}"
          p:username="${spring.datasource.username}"
          p:password="${spring.datasource.password}"
          p:initialSize="5"
          p:maxActive="10"/>

    <bean id="jpaVendorAdapter" class="org.springframework.orm.jpa.vendor.HibernateJpaVendorAdapter"
          p:database="MYSQL"
          p:showSql="true"
          p:generateDdl="false"
          p:databasePlatform="org.hibernate.dialect.MySQLDialect"/>

    <bean id="emf" class="org.springframework.orm.jpa.LocalContainerEntityManagerFactoryBean"
          p:dataSource-ref="dataSource"
          p:jpaVendorAdapter-ref="jpaVendorAdapter"
          p:packagesToScan="com.domain"/>

    <bean class="org.springframework.orm.jpa.support.PersistenceAnnotationBeanPostProcessor"/>
    <bean class="org.springframework.dao.annotation.PersistenceExceptionTranslationPostProcessor"/>

    <bean id="transactionManager" class="org.springframework.orm.jpa.JpaTransactionManager"
          p:entityManagerFactory-ref="emf"/>

    <bean class="org.springframework.beans.factory.config.PropertyPlaceholderConfigurer">
        <property name="locations" value="classpath:*.properties" />
    </bean>
</beans>